README.md
setup.py
vumasms/VumaSMS.py
vumasms/__init__.py
vumasms/test.py
vumasms.egg-info/PKG-INFO
vumasms.egg-info/SOURCES.txt
vumasms.egg-info/dependency_links.txt
vumasms.egg-info/not-zip-safe
vumasms.egg-info/top_level.txt