Metadata-Version: 1.0
Name: vumasms
Version: 0.2
Summary: VumaSMS REST API client for Python. API support for bulk SMS, Numbers, Verify (2FA) and more.
Home-page: https://github.com/Kreateyou/vumasms-python.git
Author: VumaSMS Team
Author-email: info@vumasms.com
License: MIT
Platform: UNKNOWN
